leekspin/tls.py
leekspin/torversions.py
leekspin/extrainfo.py
leekspin/generator.py
leekspin/ntor.py
leekspin/crypto.py
leekspin/server.py
leekspin/nicknames.py
leekspin/netstatus.py
leekspin/util.py
leekspin/const.py
leekspin/__init__.py
leekspin/_version.py
leekspin/rsa.py
leekspin-0.1.3.dist-info/top_level.txt
leekspin-0.1.3.dist-info/WHEEL
leekspin-0.1.3.dist-info/pydist.json
leekspin-0.1.3.dist-info/DESCRIPTION.rst
leekspin-0.1.3.dist-info/METADATA
leekspin-0.1.3.dist-info/RECORD
leekspin-0.1.3.data/scripts/leekspin
