Metadata-Version: 2.0
Name: leekspin
Version: 0.1.3
Summary: An Onion Router descriptor generator
Home-page: https://www.torproject.org
Author: isis
Author-email: isis@torproject.org 0xA3ADB67A2CDB8B35
License: MIT license
Download-URL: https://gitweb.torproject.org/user/isis/leekspin.git
Platform: UNKNOWN
Provides-Extra: test
Requires-Dist: sure (==0.4.5); extra == 'test'
Requires-Dist: coverage (==3.6); extra == 'test'
Provides-Extra: ntor
Requires-Dist: PyNaCl (==0.2.3); extra == 'ntor'
